converter/__init__.py
converter/gguf_writer.py
converter/main.py
converter/model_loader.py
converter/quantize.py
gguf_converter-0.3.1.dist-info/LICENSE
gguf_converter-0.3.1.dist-info/METADATA
gguf_converter-0.3.1.dist-info/WHEEL
gguf_converter-0.3.1.dist-info/entry_points.txt
gguf_converter-0.3.1.dist-info/top_level.txt
gguf_converter-0.3.1.dist-info/RECORD
