Metadata-Version: 2.2
Name: gguf-converter
Version: 0.3.1
Summary: Advanced Hugging Face to GGUF Converter with Quantization
Home-page: https://github.com/kunaalgadhalay/gguf-converter
Author: Your Name
Author-email: kunaalgadhalay93@gmail.com
Project-URL: Bug Reports, https://github.com/yourorg/gguf-converter/issues
Project-URL: Source, https://github.com/yourorg/gguf-converter
Keywords: gguf,quantization,transformers,llm
Classifier: Development Status :: 4 - Beta
Classifier: Intended Audience :: Developers
Classifier: Topic :: Scientific/Engineering :: Artificial Intelligence
Classifier: License :: OSI Approved :: Apache Software License
Classifier: Programming Language :: Python :: 3.9
Classifier: Programming Language :: Python :: 3.10
Classifier: Programming Language :: Python :: 3.11
Requires-Python: >=3.9, <4
License-File: LICENSE
Requires-Dist: numpy>=1.22
Requires-Dist: torch>=2.0.1
Requires-Dist: transformers>=4.31.0
Requires-Dist: accelerate>=0.21.0
Requires-Dist: safetensors>=0.3.3
Requires-Dist: tqdm>=4.66.1
Requires-Dist: psutil>=5.9.5
Provides-Extra: gpu
Requires-Dist: cudnn>=8.9.5; extra == "gpu"
Requires-Dist: nvidia-cublas-cu12>=12.1.3.1; extra == "gpu"
Provides-Extra: quantization
Requires-Dist: bitsandbytes>=0.41.1; extra == "quantization"
Requires-Dist: scipy>=1.11.1; extra == "quantization"
Provides-Extra: testing
Requires-Dist: pytest>=7.4.0; extra == "testing"
Requires-Dist: pytest-benchmark>=4.0.0; extra == "testing"
Dynamic: author
Dynamic: author-email
Dynamic: classifier
Dynamic: description
Dynamic: description-content-type
Dynamic: home-page
Dynamic: keywords
Dynamic: project-url
Dynamic: provides-extra
Dynamic: requires-dist
Dynamic: requires-python
Dynamic: summary
